AUTHORS.rst
HISTORY.rst
LICENSE
MANIFEST.in
README.rst
pyproject.toml
setup.cfg
setup.py
qblox_instruments/__init__.py
qblox_instruments/build.py
qblox_instruments/constants.py
qblox_instruments/docstring_helpers.py
qblox_instruments/types.py
qblox_instruments.egg-info/PKG-INFO
qblox_instruments.egg-info/SOURCES.txt
qblox_instruments.egg-info/dependency_links.txt
qblox_instruments.egg-info/entry_points.txt
qblox_instruments.egg-info/not-zip-safe
qblox_instruments.egg-info/requires.txt
qblox_instruments.egg-info/top_level.txt
qblox_instruments/assemblers/q1asm_linux
qblox_instruments/assemblers/q1asm_macos
qblox_instruments/assemblers/q1asm_windows.exe
qblox_instruments/cfg_man/__init__.py
qblox_instruments/cfg_man/const.py
qblox_instruments/cfg_man/log.py
qblox_instruments/cfg_man/main.py
qblox_instruments/cfg_man/pnp_connection.py
qblox_instruments/cfg_man/probe.py
qblox_instruments/cfg_man/scpi_connection.py
qblox_instruments/cfg_man/update_file.py
qblox_instruments/ieee488_2/__init__.py
qblox_instruments/ieee488_2/cluster_dummy_transport.py
qblox_instruments/ieee488_2/dummy_transport.py
qblox_instruments/ieee488_2/ieee488_2.py
qblox_instruments/ieee488_2/ip_transport.py
qblox_instruments/ieee488_2/module_dummy_transport.py
qblox_instruments/ieee488_2/transport.py
qblox_instruments/native/__init__.py
qblox_instruments/native/cluster.py
qblox_instruments/native/cluster_legacy.py
qblox_instruments/native/definitions.py
qblox_instruments/native/generic_func.py
qblox_instruments/native/helpers.py
qblox_instruments/native/spi_rack.py
qblox_instruments/native/spi_rack_modules/__init__.py
qblox_instruments/native/spi_rack_modules/d5a_module.py
qblox_instruments/native/spi_rack_modules/s4g_module.py
qblox_instruments/native/spi_rack_modules/spi_module_base.py
qblox_instruments/pnp/__init__.py
qblox_instruments/pnp/main.py
qblox_instruments/pnp/resolve.py
qblox_instruments/qcodes_drivers/__init__.py
qblox_instruments/qcodes_drivers/cluster.py
qblox_instruments/qcodes_drivers/component.py
qblox_instruments/qcodes_drivers/io_channel_qsm.py
qblox_instruments/qcodes_drivers/io_channel_qtm.py
qblox_instruments/qcodes_drivers/io_pulse_channel.py
qblox_instruments/qcodes_drivers/module.py
qblox_instruments/qcodes_drivers/quad.py
