Metadata-Version: 2.4
Name: qblox_instruments
Version: 1.1.0
Summary: Instrument drivers for Qblox devices.
Home-page: https://gitlab.com/qblox/packages/software/qblox_instruments
Download-URL: https://gitlab.com/qblox/packages/software/qblox_instruments/-/archive/v1.1.0/qblox_instruments-v1.1.0.zip
Author: Qblox BV
Author-email: Qblox BV <support@qblox.com>
License-Expression: BSD-4-Clause
Project-URL: Homepage, https://www.qblox.com/
Project-URL: Documentation, https://docs.qblox.com/en/main/index.html
Project-URL: Repository, https://gitlab.com/qblox/packages/software/qblox_instruments
Project-URL: Bug Tracker, https://gitlab.com/qblox/packages/software/qblox_instruments/-/issues
Project-URL: Changelog, https://gitlab.com/qblox/packages/software/qblox_instruments/-/blob/main/HISTORY.rst
Keywords: Qblox,QCoDeS,instrument,driver
Classifier: Development Status :: 4 - Beta
Classifier: Intended Audience :: Developers
Classifier: Natural Language :: English
Classifier: Programming Language :: Python :: 3
Classifier: Programming Language :: Python :: 3.9
Classifier: Programming Language :: Python :: 3.10
Classifier: Programming Language :: Python :: 3.11
Classifier: Programming Language :: Python :: 3.12
Classifier: Programming Language :: Python :: 3.13
Requires-Python: >=3.9
License-File: LICENSE
License-File: AUTHORS.rst
Requires-Dist: fastjsonschema
Requires-Dist: ifaddr
Requires-Dist: numpy
Requires-Dist: qcodes!=0.41.0,>=0.20.0
Requires-Dist: spirack
Requires-Dist: PySquashfsImage
Requires-Dist: configparser
Requires-Dist: strenum
Provides-Extra: dev
Requires-Dist: pytest; extra == "dev"
Requires-Dist: pytest-cov; extra == "dev"
Requires-Dist: pytest-mock; extra == "dev"
Requires-Dist: pytest-runner; extra == "dev"
Requires-Dist: ruff==0.12.*; extra == "dev"
Requires-Dist: scipy; extra == "dev"
Requires-Dist: twine!=5.1.0; extra == "dev"
Requires-Dist: typos; extra == "dev"
Dynamic: author
Dynamic: download-url
Dynamic: home-page
Dynamic: license-file
Dynamic: requires-python
